COMDIRAC/__init__.py
COMDIRAC/Interfaces/__init__.py
COMDIRAC/Interfaces/Utilities/DCommands.py
COMDIRAC/Interfaces/Utilities/DConfigCache.py
COMDIRAC/Interfaces/Utilities/__init__.py
COMDIRAC/Interfaces/scripts/dcd.py
COMDIRAC/Interfaces/scripts/dchgrp.py
COMDIRAC/Interfaces/scripts/dchmod.py
COMDIRAC/Interfaces/scripts/dchown.py
COMDIRAC/Interfaces/scripts/dconfig.py
COMDIRAC/Interfaces/scripts/dfind.py
COMDIRAC/Interfaces/scripts/dget.py
COMDIRAC/Interfaces/scripts/dgetenv.py
COMDIRAC/Interfaces/scripts/dinit.py
COMDIRAC/Interfaces/scripts/dinput.py
COMDIRAC/Interfaces/scripts/dkill.py
COMDIRAC/Interfaces/scripts/dlogging.py
COMDIRAC/Interfaces/scripts/dls.py
COMDIRAC/Interfaces/scripts/dmeta.py
COMDIRAC/Interfaces/scripts/dmkdir.py
COMDIRAC/Interfaces/scripts/doutput.py
COMDIRAC/Interfaces/scripts/dput.py
COMDIRAC/Interfaces/scripts/dpwd.py
COMDIRAC/Interfaces/scripts/drepl.py
COMDIRAC/Interfaces/scripts/dreplicas.py
COMDIRAC/Interfaces/scripts/drm.py
COMDIRAC/Interfaces/scripts/drmdir.py
COMDIRAC/Interfaces/scripts/dsetenv.py
COMDIRAC/Interfaces/scripts/dsize.py
COMDIRAC/Interfaces/scripts/dstat.py
COMDIRAC/Interfaces/scripts/dsub.py
COMDIRAC/Interfaces/scripts/dunsetenv.py
COMDIRAC-1.3.3.dist-info/LICENSE
COMDIRAC-1.3.3.dist-info/METADATA
COMDIRAC-1.3.3.dist-info/WHEEL
COMDIRAC-1.3.3.dist-info/entry_points.txt
COMDIRAC-1.3.3.dist-info/top_level.txt
COMDIRAC-1.3.3.dist-info/RECORD
